platypy/Fontschanger.py
platypy/__init__.py
platypy/coolcalci.py
platypy/createquestionsandanswers.py
platypy-3.1.2.dist-info/METADATA
platypy-3.1.2.dist-info/WHEEL
platypy-3.1.2.dist-info/top_level.txt
platypy-3.1.2.dist-info/RECORD
