Metadata-Version: 2.1
Name: platypy
Version: 3.1.2
Summary: This platypy which have many submodules to help you.
Home-page: UNKNOWN
Author: Python Rohan
Author-email: rohan9878787@gmail.com
License: UNKNOWN
Keywords: python,calculator,calci,calculate,calculation,Arithmetic
Platform: UNKNOWN
Classifier: Development Status :: 1 - Planning
Classifier: Intended Audience :: Developers
Classifier: Programming Language :: Python :: 3
Classifier: Operating System :: Unix
Classifier: Operating System :: MacOS :: MacOS X
Classifier: Operating System :: Microsoft :: Windows
